{
    "title": "Lab 2 - Deploy App - Flux Repo",
    "description": "Deploying manifests from Flux repo using Source and Kustomize Controller",
    "details": {
      "intro": {
        "foreground": "foreground.sh",
        "background": "background.sh",
        "text": "intro.md"
      },
      "steps": [
        {
          "title": "1. Install Flux Server",
          "text": "step1.md"
        },
        {
          "title": "2. Explore GitHub Repo",
          "text": "step2.md"
        },
        {
          "title": "3. Commit Manifest Files",
          "text": "step3.md"
        },
        {
          "title": "4. Access the Application",
          "text": "step4.md"
        },
        {
          "title": "5. Manual Reconcilation",
          "text": "step5.md"
        }
      ],
      "finish": {
        "text": "finish.md"
      }
    },
    "backend": {
      "imageid": "kubernetes-kubeadm-1node"
    }
  }
  